numcore/Library.py
numcore/__init__.py
numcore-0.1.7.dist-info/licenses/License
numcore-0.1.7.dist-info/METADATA
numcore-0.1.7.dist-info/WHEEL
numcore-0.1.7.dist-info/top_level.txt
numcore-0.1.7.dist-info/RECORD
