Metadata-Version: 2.4
Name: numcore
Version: 0.1.7
Summary: A mathematics library in active development with plans for 250+ functions. Started by a first-year student, built from scratch, and designed to become a comprehensive math toolkit
Author-email: ujwal mantri <ujwalmantrifr@gmail.com>
License: MIT License
License-File: License
Dynamic: license-file
